jinja_wtforms/__init__.py
jinja_wtforms/extractor.py
jinja_wtforms/form.py
jinja_wtforms/registry.py
jinja_wtforms-0.2.1.dist-info/WHEEL
jinja_wtforms-0.2.1.dist-info/METADATA
jinja_wtforms-0.2.1.dist-info/RECORD
