Metadata-Version: 2.4
Name: jinja-wtforms
Version: 0.2.1
Summary: Create wtforms from Jinja templates
Author: Maxime Bouroumeau-Fuseau
Author-email: Maxime Bouroumeau-Fuseau <maxime.bouroumeau@gmail.com>
License-Expression: MIT
Requires-Dist: jinja2>=3.0.0,<4.0.0
Requires-Dist: wtforms>=3.0.0,<4.0.0
Requires-Python: >=3.10
Project-URL: Repository, https://github.com/hyperflask/jinja-wtforms
